[{"lat": 0, "lon": 0, "order_date": "2023-01-09", "order_total": 6678367.81, "order_total_count": 190490, "risk_score_count": 190490, "risk_score": 1.45}, {"lat": -6.21, "lon": 106.85, "order_date": "2023-01-09", "order_total": 6272.38, "order_total_count": 6772, "risk_score_count": 6772, "risk_score": 3.75}, {"lat": 38.28146, "lon": -85.57289, "order_date": "2023-01-09", "order_total": 113818.47, "order_total_count": 549, "risk_score_count": 132, "risk_score": 1.05}, {"lat": 52.38, "lon": 5.79, "order_date": "2023-01-09", "order_total": 416468.1, "order_total_count": 3868, "risk_score_count": 3868, "risk_score": 1.16}, {"lat": 33.85266, "lon": -117.99279, "order_date": "2023-01-09", "order_total": 332605.04, "order_total_count": 881, "risk_score_count": 427, "risk_score": 1.07}, {"lat": 26.4711, "lon": 49.7978, "order_date": "2023-01-09", "order_total": 45590.54, "order_total_count": 100, "risk_score_count": 100, "risk_score": 2.2}, {"lat": 7.74, "lon": 99.4, "order_date": "2023-01-09", "order_total": 2681.59, "order_total_count": 123, "risk_score_count": 123, "risk_score": 2.89}, {"lat": -23.4319, "lon": -46.4694, "order_date": "2023-01-09", "order_total": 28733.22, "order_total_count": 46, "risk_score_count": 46, "risk_score": 1.5}, {"lat": 46.99, "lon": 6.93, "order_date": "2023-01-09", "order_total": 73638.79, "order_total_count": 795, "risk_score_count": 795, "risk_score": 1.99}, {"lat": 26.01259, "lon": -80.35524, "order_date": "2023-01-09", "order_total": 190216.07, "order_total_count": 520, "risk_score_count": 381, "risk_score": 1.15}, {"lat": 48.19, "lon": 11.64, "order_date": "2023-01-09", "order_total": 1559361.35, "order_total_count": 9571, "risk_score_count": 9571, "risk_score": 2.0}, {"lat": 13.4839, "lon": 144.7972, "order_date": "2023-01-09", "order_total": 10651.96, "order_total_count": 12, "risk_score_count": 9, "risk_score": 1.56}, {"lat": 39.82, "lon": 34.8, "order_date": "2023-01-09", "order_total": 2216.73, "order_total_count": 207, "risk_score_count": 207, "risk_score": 2.61}, {"lat": 30.1715, "lon": -95.19966, "order_date": "2023-01-09", "order_total": 128410.21, "order_total_count": 425, "risk_score_count": 188, "risk_score": 1.11}, {"lat": 53.2, "lon": -1.87, "order_date": "2023-01-09", "order_total": 26670.48, "order_total_count": 1429, "risk_score_count": 1429, "risk_score": 2.54}, {"lat": 40.87826, "lon": -74.25753, "order_date": "2023-01-09", "order_total": 699380.39, "order_total_count": 1626, "risk_score_count": 834, "risk_score": 1.09}, {"lat": -33.82, "lon": 151.0, "order_date": "2023-01-09", "order_total": 41284.23, "order_total_count": 50, "risk_score_count": 46, "risk_score": 1.74}, {"lat": 45.83798, "lon": -115.45212, "order_date": "2023-01-09", "order_total": 20923.0, "order_total_count": 145, "risk_score_count": 24, "risk_score": 1.17}, {"lat": 0.91, "lon": 123.31, "order_date": "2023-01-09", "order_total": 834.35, "order_total_count": 140, "risk_score_count": 140, "risk_score": 3.41}, {"lat": -7.68, "lon": 112.62, "order_date": "2023-01-09", "order_total": 1316.98, "order_total_count": 1509, "risk_score_count": 1509, "risk_score": 3.61}, {"lat": 43.38, "lon": 1.18, "order_date": "2023-01-09", "order_total": 7201.51, "order_total_count": 361, "risk_score_count": 360, "risk_score": 2.07}, {"lat": 3.4575, "lon": -76.4964, "order_date": "2023-01-09", "order_total": 93706.18, "order_total_count": 135, "risk_score_count": 135, "risk_score": 2.06}, {"lat": 39.12613, "lon": -104.91073, "order_date": "2023-01-09", "order_total": 102768.06, "order_total_count": 422, "risk_score_count": 154, "risk_score": 1.1}, {"lat": 21.29184, "lon": -157.70759, "order_date": "2023-01-09", "order_total": 35616.52, "order_total_count": 74, "risk_score_count": 44, "risk_score": 1.07}, {"lat": 22.29, "lon": 114.16, "order_date": "2023-01-09", "order_total": 9392.13, "order_total_count": 54, "risk_score_count": 54, "risk_score": 2.93}, {"lat": 13.58, "lon": 100.82, "order_date": "2023-01-09", "order_total": 93811.99, "order_total_count": 922, "risk_score_count": 922, "risk_score": 2.98}, {"lat": 51.02, "lon": 11.91, "order_date": "2023-01-09", "order_total": 69282.63, "order_total_count": 904, "risk_score_count": 904, "risk_score": 2.09}, {"lat": 40.03276, "lon": -95.72295, "order_date": "2023-01-09", "order_total": 57564.65, "order_total_count": 247, "risk_score_count": 64, "risk_score": 1.05}, {"lat": 12.9667, "lon": 77.6, "order_date": "2023-01-09", "order_total": 73904.99, "order_total_count": 51, "risk_score_count": 51, "risk_score": 1.51}, {"lat": 13.25, "lon": -61.3667, "order_date": "2023-01-09", "order_total": 34215.73, "order_total_count": 51, "risk_score_count": 51, "risk_score": 1.25}, {"lat": 61.53322, "lon": -149.48187, "order_date": "2023-01-09", "order_total": 11931.21, "order_total_count": 46, "risk_score_count": 11, "risk_score": 1.09}, {"lat": 35.1, "lon": 138.84, "order_date": "2023-01-09", "order_total": 42387.02, "order_total_count": 70, "risk_score_count": 70, "risk_score": 3.0}, {"lat": 48.9, "lon": 2.31, "order_date": "2023-01-09", "order_total": 54789.95, "order_total_count": 2029, "risk_score_count": 2029, "risk_score": 2.24}, {"lat": 53.55, "lon": 10.06, "order_date": "2023-01-09", "order_total": 166807.1, "order_total_count": 1700, "risk_score_count": 1700, "risk_score": 2.05}, {"lat": 1.3167, "lon": 36.9333, "order_date": "2023-01-09", "order_total": 22588.2, "order_total_count": 22, "risk_score_count": 22, "risk_score": 2.23}, {"lat": 3.68, "lon": 101.52, "order_date": "2023-01-09", "order_total": 6434.77, "order_total_count": 287, "risk_score_count": 287, "risk_score": 2.13}, {"lat": 52.4, "lon": 13.06, "order_date": "2023-01-09", "order_total": 527750.9, "order_total_count": 3024, "risk_score_count": 3024, "risk_score": 2.07}, {"lat": 42.36564, "lon": -88.08509, "order_date": "2023-01-09", "order_total": 234539.76, "order_total_count": 728, "risk_score_count": 253, "risk_score": 1.04}, {"lat": -37.0081, "lon": 174.7917, "order_date": "2023-01-09", "order_total": 31608.75, "order_total_count": 39, "risk_score_count": 39, "risk_score": 1.28}, {"lat": 34.5658, "lon": 69.2122, "order_date": "2023-01-09", "order_total": 10930.9, "order_total_count": 26, "risk_score_count": 26, "risk_score": 2.69}, {"lat": 42.4652, "lon": -122.80657, "order_date": "2023-01-09", "order_total": 17978.95, "order_total_count": 80, "risk_score_count": 15, "risk_score": 1.0}, {"lat": 40.9769, "lon": 28.8211, "order_date": "2023-01-09", "order_total": 20399.08, "order_total_count": 418, "risk_score_count": 418, "risk_score": 2.59}, {"lat": 51.96, "lon": 7.63, "order_date": "2023-01-09", "order_total": 145324.71, "order_total_count": 1623, "risk_score_count": 1623, "risk_score": 1.96}, {"lat": 37.7, "lon": -6.55, "order_date": "2023-01-09", "order_total": 5136.91, "order_total_count": 121, "risk_score_count": 121, "risk_score": 2.0}, {"lat": -5.67, "lon": 132.75, "order_date": "2023-01-09", "order_total": 66.86, "order_total_count": 40, "risk_score_count": 40, "risk_score": 3.65}, {"lat": 36.34615, "lon": -78.39242, "order_date": "2023-01-09", "order_total": 90928.18, "order_total_count": 442, "risk_score_count": 102, "risk_score": 1.06}, {"lat": 20.51, "lon": -86.95, "order_date": "2023-01-09", "order_total": 12355.43, "order_total_count": 28, "risk_score_count": 28, "risk_score": 1.57}, {"lat": 52.09, "lon": 20.39, "order_date": "2023-01-09", "order_total": 11417.07, "order_total_count": 237, "risk_score_count": 237, "risk_score": 2.04}, {"lat": 33.90207, "lon": -84.81114, "order_date": "2023-01-09", "order_total": 119786.04, "order_total_count": 653, "risk_score_count": 186, "risk_score": 1.05}, {"lat": -0.5, "lon": 117.15, "order_date": "2023-01-09", "order_total": 236.39, "order_total_count": 305, "risk_score_count": 305, "risk_score": 3.6}, {"lat": 51.53, "lon": -0.17, "order_date": "2023-01-09", "order_total": 56360.33, "order_total_count": 1491, "risk_score_count": 1491, "risk_score": 2.58}, {"lat": 48.02, "lon": 13.65, "order_date": "2023-01-09", "order_total": 38198.05, "order_total_count": 374, "risk_score_count": 374, "risk_score": 2.13}, {"lat": 28.5694, "lon": 77.1181, "order_date": "2023-01-09", "order_total": 96569.0, "order_total_count": 68, "risk_score_count": 68, "risk_score": 1.81}, {"lat": 41.22114, "lon": -80.48048, "order_date": "2023-01-09", "order_total": 84720.87, "order_total_count": 485, "risk_score_count": 108, "risk_score": 1.15}, {"lat": 42.16307, "lon": -92.01817, "order_date": "2023-01-09", "order_total": 21690.09, "order_total_count": 119, "risk_score_count": 14, "risk_score": 1.21}, {"lat": 13.28, "lon": 121.3, "order_date": "2023-01-09", "order_total": 181196.68, "order_total_count": 151, "risk_score_count": 151, "risk_score": 1.77}, {"lat": -33.9833, "lon": 25.6167, "order_date": "2023-01-09", "order_total": 8221.66, "order_total_count": 7, "risk_score_count": 7, "risk_score": 1.57}, {"lat": -8.65, "lon": 115.22, "order_date": "2023-01-09", "order_total": 3237.96, "order_total_count": 395, "risk_score_count": 395, "risk_score": 3.57}, {"lat": -33.5597, "lon": -70.7, "order_date": "2023-01-09", "order_total": 8108.53, "order_total_count": 11, "risk_score_count": 11, "risk_score": 1.45}, {"lat": 59.76, "lon": 18.7, "order_date": "2023-01-09", "order_total": 129676.19, "order_total_count": 195, "risk_score_count": 195, "risk_score": 1.77}, {"lat": 0.83, "lon": 109.44, "order_date": "2023-01-09", "order_total": 221.22, "order_total_count": 191, "risk_score_count": 191, "risk_score": 3.32}, {"lat": 51.87, "lon": 4.66, "order_date": "2023-01-09", "order_total": 741296.15, "order_total_count": 7488, "risk_score_count": 7488, "risk_score": 1.23}, {"lat": 20.68, "lon": -105.2542, "order_date": "2023-01-09", "order_total": 24944.51, "order_total_count": 35, "risk_score_count": 35, "risk_score": 1.2}, {"lat": 25.04, "lon": 121.56, "order_date": "2023-01-09", "order_total": 14472.05, "order_total_count": 31, "risk_score_count": 31, "risk_score": 2.71}, {"lat": 28.57615, "lon": -81.80199, "order_date": "2023-01-09", "order_total": 178397.77, "order_total_count": 688, "risk_score_count": 350, "risk_score": 1.09}, {"lat": 33.20005, "lon": -111.52112, "order_date": "2023-01-09", "order_total": 72907.38, "order_total_count": 285, "risk_score_count": 120, "risk_score": 1.06}, {"lat": 6.4986, "lon": -58.2542, "order_date": "2023-01-09", "order_total": 21048.51, "order_total_count": 24, "risk_score_count": 24, "risk_score": 2.04}, {"lat": -12.0219, "lon": -77.1144, "order_date": "2023-01-09", "order_total": 25591.28, "order_total_count": 42, "risk_score_count": 42, "risk_score": 1.43}, {"lat": 46.83766, "lon": -122.4786, "order_date": "2023-01-09", "order_total": 139349.63, "order_total_count": 410, "risk_score_count": 146, "risk_score": 1.08}, {"lat": 21.27, "lon": 40.42, "order_date": "2023-01-09", "order_total": 12173.58, "order_total_count": 65, "risk_score_count": 65, "risk_score": 2.49}, {"lat": 41.3211, "lon": -111.94338, "order_date": "2023-01-09", "order_total": 34846.25, "order_total_count": 165, "risk_score_count": 39, "risk_score": 1.05}, {"lat": 43.94, "lon": 5.77, "order_date": "2023-01-09", "order_total": 16790.18, "order_total_count": 741, "risk_score_count": 741, "risk_score": 2.26}, {"lat": 18.63, "lon": 99.12, "order_date": "2023-01-09", "order_total": 8883.38, "order_total_count": 141, "risk_score_count": 141, "risk_score": 2.87}, {"lat": -7.53, "lon": 110.6, "order_date": "2023-01-09", "order_total": 1194.05, "order_total_count": 1599, "risk_score_count": 1599, "risk_score": 3.74}, {"lat": -34.5592, "lon": -58.4156, "order_date": "2023-01-09", "order_total": 42217.07, "order_total_count": 39, "risk_score_count": 39, "risk_score": 1.82}, {"lat": 33.36568, "lon": -97.17661, "order_date": "2023-01-09", "order_total": 135451.17, "order_total_count": 470, "risk_score_count": 181, "risk_score": 1.07}, {"lat": 25.26, "lon": 55.3, "order_date": "2023-01-09", "order_total": 46462.0, "order_total_count": 302, "risk_score_count": 302, "risk_score": 2.44}, {"lat": 31.16, "lon": 31.94, "order_date": "2023-01-09", "order_total": 81595.97, "order_total_count": 114, "risk_score_count": 114, "risk_score": 2.41}, {"lat": 59.49, "lon": 10.32, "order_date": "2023-01-09", "order_total": 241328.84, "order_total_count": 240, "risk_score_count": 240, "risk_score": 1.4}, {"lat": 42.76473, "lon": -71.08947, "order_date": "2023-01-09", "order_total": 173643.32, "order_total_count": 566, "risk_score_count": 205, "risk_score": 1.18}, {"lat": 34.77637, "lon": -80.9628, "order_date": "2023-01-09", "order_total": 103937.14, "order_total_count": 478, "risk_score_count": 118, "risk_score": 1.11}, {"lat": -31.9403, "lon": 115.9669, "order_date": "2023-01-09", "order_total": 6165.07, "order_total_count": 10, "risk_score_count": 10, "risk_score": 1.6}, {"lat": 37.95113, "lon": -121.69619, "order_date": "2023-01-09", "order_total": 232524.08, "order_total_count": 589, "risk_score_count": 258, "risk_score": 1.17}, {"lat": -0.53, "lon": 101.58, "order_date": "2023-01-09", "order_total": 351.39, "order_total_count": 278, "risk_score_count": 278, "risk_score": 3.58}, {"lat": -20.88, "lon": 55.45, "order_date": "2023-01-09", "order_total": 152.94, "order_total_count": 9, "risk_score_count": 9, "risk_score": 2.11}, {"lat": 45.31825, "lon": -93.74575, "order_date": "2023-01-09", "order_total": 56394.93, "order_total_count": 320, "risk_score_count": 62, "risk_score": 1.02}, {"lat": 19.25, "lon": -69.7, "order_date": "2023-01-09", "order_total": 49832.09, "order_total_count": 90, "risk_score_count": 90, "risk_score": 1.43}, {"lat": 9.9939, "lon": -84.2089, "order_date": "2023-01-09", "order_total": 27873.68, "order_total_count": 32, "risk_score_count": 32, "risk_score": 1.31}, {"lat": -3.01, "lon": 114.39, "order_date": "2023-01-09", "order_total": 231.43, "order_total_count": 307, "risk_score_count": 307, "risk_score": 3.59}, {"lat": 27.76, "lon": -15.59, "order_date": "2023-01-09", "order_total": 1440.55, "order_total_count": 28, "risk_score_count": 28, "risk_score": 1.89}, {"lat": 48.7, "lon": 9.65, "order_date": "2023-01-09", "order_total": 91223.29, "order_total_count": 891, "risk_score_count": 891, "risk_score": 2.12}, {"lat": 30.79491, "lon": -89.24302, "order_date": "2023-01-09", "order_total": 38371.41, "order_total_count": 261, "risk_score_count": 53, "risk_score": 1.13}, {"lat": 48.11, "lon": -1.67, "order_date": "2023-01-09", "order_total": 5016.55, "order_total_count": 299, "risk_score_count": 298, "risk_score": 2.1}, {"lat": 40.63, "lon": -3.17, "order_date": "2023-01-09", "order_total": 9031.38, "order_total_count": 210, "risk_score_count": 210, "risk_score": 2.08}, {"lat": -17.75, "lon": 177.45, "order_date": "2023-01-09", "order_total": 10263.72, "order_total_count": 8, "risk_score_count": 8, "risk_score": 1.25}, {"lat": 23.8433, "lon": 90.3978, "order_date": "2023-01-09", "order_total": 54033.95, "order_total_count": 28, "risk_score_count": 28, "risk_score": 2.07}, {"lat": 3.76, "lon": 98.45, "order_date": "2023-01-09", "order_total": 590.89, "order_total_count": 647, "risk_score_count": 647, "risk_score": 3.6}, {"lat": -3.7764, "lon": -38.5325, "order_date": "2023-01-09", "order_total": 5461.17, "order_total_count": 15, "risk_score_count": 15, "risk_score": 2.07}, {"lat": -4.54, "lon": 120.33, "order_date": "2023-01-09", "order_total": 399.83, "order_total_count": 239, "risk_score_count": 239, "risk_score": 3.61}, {"lat": 50.81, "lon": 6.52, "order_date": "2023-01-09", "order_total": 297406.3, "order_total_count": 2616, "risk_score_count": 2616, "risk_score": 1.94}, {"lat": 54.47, "lon": -6.33, "order_date": "2023-01-09", "order_total": 9500.77, "order_total_count": 152, "risk_score_count": 152, "risk_score": 2.36}, {"lat": 48.38, "lon": 16.22, "order_date": "2023-01-09", "order_total": 45192.62, "order_total_count": 451, "risk_score_count": 451, "risk_score": 2.15}, {"lat": 35.81883, "lon": -94.12921, "order_date": "2023-01-09", "order_total": 34392.31, "order_total_count": 174, "risk_score_count": 32, "risk_score": 1.0}, {"lat": 30.23991, "lon": -98.65711, "order_date": "2023-01-09", "order_total": 85608.73, "order_total_count": 370, "risk_score_count": 112, "risk_score": 1.11}, {"lat": 46.05475, "lon": -104.2445, "order_date": "2023-01-09", "order_total": 8041.12, "order_total_count": 64, "risk_score_count": 10, "risk_score": 1.5}, {"lat": 38.02, "lon": 40.18, "order_date": "2023-01-09", "order_total": 14885.08, "order_total_count": 159, "risk_score_count": 159, "risk_score": 2.5}, {"lat": 15.3, "lon": 101.36, "order_date": "2023-01-09", "order_total": 110.74, "order_total_count": 224, "risk_score_count": 224, "risk_score": 3.0}, {"lat": 10.45, "lon": -75.5167, "order_date": "2023-01-09", "order_total": 22376.0, "order_total_count": 44, "risk_score_count": 44, "risk_score": 2.18}, {"lat": 50.01, "lon": 8.35, "order_date": "2023-01-09", "order_total": 203535.45, "order_total_count": 2028, "risk_score_count": 2028, "risk_score": 2.07}, {"lat": 52.23, "lon": 9.09, "order_date": "2023-01-09", "order_total": 107057.3, "order_total_count": 1168, "risk_score_count": 1168, "risk_score": 2.1}, {"lat": 42.36, "lon": 20.82, "order_date": "2023-01-09", "order_total": 24333.66, "order_total_count": 65, "risk_score_count": 65, "risk_score": 1.69}, {"lat": 56.01, "lon": -3.72, "order_date": "2023-01-09", "order_total": 8408.33, "order_total_count": 343, "risk_score_count": 343, "risk_score": 2.44}, {"lat": 37.48, "lon": 126.87, "order_date": "2023-01-09", "order_total": 23671.73, "order_total_count": 37, "risk_score_count": 37, "risk_score": 2.05}, {"lat": 39.21859, "lon": -76.99723, "order_date": "2023-01-09", "order_total": 208671.96, "order_total_count": 720, "risk_score_count": 253, "risk_score": 1.13}, {"lat": -17.6447, "lon": -63.1353, "order_date": "2023-01-09", "order_total": 13508.9, "order_total_count": 11, "risk_score_count": 11, "risk_score": 1.91}, {"lat": 16.33, "lon": 103.3, "order_date": "2023-01-09", "order_total": 4478.54, "order_total_count": 243, "risk_score_count": 243, "risk_score": 2.95}, {"lat": -13.8333, "lon": -172.0, "order_date": "2023-01-09", "order_total": 1862.6, "order_total_count": 2, "risk_score_count": 2, "risk_score": 1.0}, {"lat": 42.15964, "lon": -83.79545, "order_date": "2023-01-09", "order_total": 113972.04, "order_total_count": 511, "risk_score_count": 128, "risk_score": 1.04}, {"lat": 26.3194, "lon": -98.19092, "order_date": "2023-01-09", "order_total": 27558.29, "order_total_count": 86, "risk_score_count": 40, "risk_score": 1.05}, {"lat": 45.46, "lon": 9.19, "order_date": "2023-01-09", "order_total": 25408.0, "order_total_count": 248, "risk_score_count": 247, "risk_score": 1.91}, {"lat": 13.4408, "lon": -89.0558, "order_date": "2023-01-09", "order_total": 54380.81, "order_total_count": 78, "risk_score_count": 78, "risk_score": 1.42}, {"lat": 53.3097, "lon": -113.5797, "order_date": "2023-01-09", "order_total": 48020.92, "order_total_count": 46, "risk_score_count": 44, "risk_score": 1.39}, {"lat": 5.34, "lon": 116.16, "order_date": "2023-01-09", "order_total": 432.95, "order_total_count": 73, "risk_score_count": 73, "risk_score": 2.25}, {"lat": 19.26, "lon": -99.11, "order_date": "2023-01-09", "order_total": 39375.58, "order_total_count": 59, "risk_score_count": 59, "risk_score": 1.24}, {"lat": 51.48, "lon": -3.18, "order_date": "2023-01-09", "order_total": 8773.72, "order_total_count": 488, "risk_score_count": 488, "risk_score": 2.51}, {"lat": 1.29, "lon": 103.85, "order_date": "2023-01-09", "order_total": 8901.19, "order_total_count": 183, "risk_score_count": 183, "risk_score": 3.04}, {"lat": -4.5, "lon": 104.52, "order_date": "2023-01-09", "order_total": 237.34, "order_total_count": 390, "risk_score_count": 390, "risk_score": 3.7}, {"lat": -2.63, "lon": 140.58, "order_date": "2023-01-09", "order_total": 6890.13, "order_total_count": 32, "risk_score_count": 32, "risk_score": 3.16}, {"lat": -15.4167, "lon": 28.3333, "order_date": "2023-01-09", "order_total": 735.82, "order_total_count": 3, "risk_score_count": 3, "risk_score": 2.0}, {"lat": 37.76679, "lon": -90.41174, "order_date": "2023-01-09", "order_total": 40806.05, "order_total_count": 277, "risk_score_count": 50, "risk_score": 1.18}, {"lat": 36.10197, "lon": -115.03114, "order_date": "2023-01-09", "order_total": 58163.19, "order_total_count": 195, "risk_score_count": 135, "risk_score": 1.24}, {"lat": 18.4447, "lon": -65.5431, "order_date": "2023-01-09", "order_total": 44098.34, "order_total_count": 111, "risk_score_count": 101, "risk_score": 1.12}, {"lat": -8.77, "lon": 120.64, "order_date": "2023-01-09", "order_total": 314.78, "order_total_count": 82, "risk_score_count": 82, "risk_score": 3.59}, {"lat": 47.4, "lon": 8.45, "order_date": "2023-01-09", "order_total": 251231.27, "order_total_count": 1824, "risk_score_count": 1823, "risk_score": 2.04}, {"lat": 18.5, "lon": -77.9167, "order_date": "2023-01-09", "order_total": 15558.82, "order_total_count": 39, "risk_score_count": 39, "risk_score": 1.23}, {"lat": -7.04, "lon": 107.91, "order_date": "2023-01-09", "order_total": 1248.35, "order_total_count": 1565, "risk_score_count": 1565, "risk_score": 3.78}]
